[
  {
    "id": 1,
    "emoji": "ac1",
    "value": "<:ac1:1103880992575455312>",
    "createdAt": "2023-05-25T14:00:12.000Z",
    "updatedAt": "2023-05-25T14:00:12.000Z"
  },
  {
    "id": 2,
    "emoji": "ah1",
    "value": "<:ah1:1103884770435399710>",
    "createdAt": "2023-05-25T14:00:12.000Z",
    "updatedAt": "2023-05-25T14:00:12.000Z"
  },
  {
    "id": 3,
    "emoji": "ad1",
    "value": "<:ad1:1103885990881394729>",
    "createdAt": "2023-05-25T14:00:12.000Z",
    "updatedAt": "2023-05-25T14:00:12.000Z"
  },
  {
    "id": 4,
    "emoji": "as1",
    "value": "<:as1:1103886514489929728>",
    "createdAt": "2023-05-25T14:00:12.000Z",
    "updatedAt": "2023-05-25T14:00:12.000Z"
  },
  {
    "id": 5,
    "emoji": "s2",
    "value": "<:s2:1103887564215173242>",
    "createdAt": "2023-05-25T14:00:12.000Z",
    "updatedAt": "2023-05-25T14:00:12.000Z"
  },
  {
    "id": 6,
    "emoji": "c2",
    "value": "<:c2:1103887639402262538>",
    "createdAt": "2023-05-25T14:00:12.000Z",
    "updatedAt": "2023-05-25T14:00:12.000Z"
  },
  {
    "id": 7,
    "emoji": "h2",
    "value": "<:h2:1103887941882884168>",
    "createdAt": "2023-05-25T14:00:12.000Z",
    "updatedAt": "2023-05-25T14:00:12.000Z"
  },
  {
    "id": 8,
    "emoji": "d2",
    "value": "<:d2:1103889739431551017>",
    "createdAt": "2023-05-25T14:00:12.000Z",
    "updatedAt": "2023-05-25T14:00:12.000Z"
  },
  {
    "id": 9,
    "emoji": "s3",
    "value": "<:s3:1103890317402452048>",
    "createdAt": "2023-05-25T14:00:12.000Z",
    "updatedAt": "2023-05-25T14:00:12.000Z"
  },
  {
    "id": 10,
    "emoji": "c3",
    "value": "<:c3:1103890489922560070>",
    "createdAt": "2023-05-25T14:00:12.000Z",
    "updatedAt": "2023-05-25T14:00:12.000Z"
  },
  {
    "id": 11,
    "emoji": "h3",
    "value": "<:h3:1103890536995233792>",
    "createdAt": "2023-05-25T14:00:12.000Z",
    "updatedAt": "2023-05-25T14:00:12.000Z"
  },
  {
    "id": 12,
    "emoji": "d3",
    "value": "<:d3:1103890580246900846>",
    "createdAt": "2023-05-25T14:00:12.000Z",
    "updatedAt": "2023-05-25T14:00:12.000Z"
  },
  {
    "id": 13,
    "emoji": "s4",
    "value": "<:s4:1103890824338604042>",
    "createdAt": "2023-05-25T14:00:12.000Z",
    "updatedAt": "2023-05-25T14:00:12.000Z"
  },
  {
    "id": 14,
    "emoji": "c4",
    "value": "<:c4:1103890863312076901>",
    "createdAt": "2023-05-25T14:00:12.000Z",
    "updatedAt": "2023-05-25T14:00:12.000Z"
  },
  {
    "id": 15,
    "emoji": "h4",
    "value": "<:h4:1103890897093009498>",
    "createdAt": "2023-05-25T14:00:12.000Z",
    "updatedAt": "2023-05-25T14:00:12.000Z"
  },
  {
    "id": 16,
    "emoji": "d4",
    "value": "<:d4:1103890936410406982>",
    "createdAt": "2023-05-25T14:00:12.000Z",
    "updatedAt": "2023-05-25T14:00:12.000Z"
  },
  {
    "id": 17,
    "emoji": "s5",
    "value": "<:s5:1103891141771931648>",
    "createdAt": "2023-05-25T14:00:12.000Z",
    "updatedAt": "2023-05-25T14:00:12.000Z"
  },
  {
    "id": 18,
    "emoji": "c5",
    "value": "<:c5:1103891173141139498>",
    "createdAt": "2023-05-25T14:00:12.000Z",
    "updatedAt": "2023-05-25T14:00:12.000Z"
  },
  {
    "id": 19,
    "emoji": "h5",
    "value": "<:h5:1103891207127576646>",
    "createdAt": "2023-05-25T14:00:12.000Z",
    "updatedAt": "2023-05-25T14:00:12.000Z"
  },
  {
    "id": 20,
    "emoji": "d5",
    "value": "<:d5:1103891242984681564>",
    "createdAt": "2023-05-25T14:00:12.000Z",
    "updatedAt": "2023-05-25T14:00:12.000Z"
  },
  {
    "id": 21,
    "emoji": "s6",
    "value": "<:s6:1103891505086742570>",
    "createdAt": "2023-05-25T14:00:12.000Z",
    "updatedAt": "2023-05-25T14:00:12.000Z"
  },
  {
    "id": 22,
    "emoji": "c6",
    "value": "<:c6:1103891529594052618>",
    "createdAt": "2023-05-25T14:00:12.000Z",
    "updatedAt": "2023-05-25T14:00:12.000Z"
  },
  {
    "id": 23,
    "emoji": "h6",
    "value": "<:h6:1103891562112491581>",
    "createdAt": "2023-05-25T14:00:12.000Z",
    "updatedAt": "2023-05-25T14:00:12.000Z"
  },
  {
    "id": 24,
    "emoji": "d6",
    "value": "<:d6:1103891589392252938>",
    "createdAt": "2023-05-25T14:00:12.000Z",
    "updatedAt": "2023-05-25T14:00:12.000Z"
  },
  {
    "id": 25,
    "emoji": "s7",
    "value": "<:s7:1103891863397728316>",
    "createdAt": "2023-05-25T14:00:12.000Z",
    "updatedAt": "2023-05-25T14:00:12.000Z"
  },
  {
    "id": 26,
    "emoji": "c7",
    "value": "<:c7:1103891885161971732>",
    "createdAt": "2023-05-25T14:00:12.000Z",
    "updatedAt": "2023-05-25T14:00:12.000Z"
  },
  {
    "id": 27,
    "emoji": "h7",
    "value": "<:h7:1103891914081714317>",
    "createdAt": "2023-05-25T14:00:12.000Z",
    "updatedAt": "2023-05-25T14:00:12.000Z"
  },
  {
    "id": 28,
    "emoji": "d7",
    "value": "<:d7:1103891952308584448>",
    "createdAt": "2023-05-25T14:00:12.000Z",
    "updatedAt": "2023-05-25T14:00:12.000Z"
  },
  {
    "id": 29,
    "emoji": "s8",
    "value": "<:s8:1103892131854164070>",
    "createdAt": "2023-05-25T14:00:12.000Z",
    "updatedAt": "2023-05-25T14:00:12.000Z"
  },
  {
    "id": 30,
    "emoji": "c8",
    "value": "<:c8:1103892163428896798>",
    "createdAt": "2023-05-25T14:00:12.000Z",
    "updatedAt": "2023-05-25T14:00:12.000Z"
  },
  {
    "id": 31,
    "emoji": "h8",
    "value": "<:h8:1103892198807842866>",
    "createdAt": "2023-05-25T14:00:12.000Z",
    "updatedAt": "2023-05-25T14:00:12.000Z"
  },
  {
    "id": 32,
    "emoji": "d8",
    "value": "<:d8:1103892234899824642>",
    "createdAt": "2023-05-25T14:00:12.000Z",
    "updatedAt": "2023-05-25T14:00:12.000Z"
  },
  {
    "id": 33,
    "emoji": "s9",
    "value": "<:s9:1103892696092913704>",
    "createdAt": "2023-05-25T14:00:12.000Z",
    "updatedAt": "2023-05-25T14:00:12.000Z"
  },
  {
    "id": 34,
    "emoji": "c9",
    "value": "<:c9:1103892727248207924>",
    "createdAt": "2023-05-25T14:00:12.000Z",
    "updatedAt": "2023-05-25T14:00:12.000Z"
  },
  {
    "id": 35,
    "emoji": "h9",
    "value": "<:h9:1103892778620030986>",
    "createdAt": "2023-05-25T14:00:12.000Z",
    "updatedAt": "2023-05-25T14:00:12.000Z"
  },
  {
    "id": 36,
    "emoji": "d9",
    "value": "<:d9:1103892904281387018>",
    "createdAt": "2023-05-25T14:00:12.000Z",
    "updatedAt": "2023-05-25T14:00:12.000Z"
  },
  {
    "id": 37,
    "emoji": "s10",
    "value": "<:s10:1103893284679602298>",
    "createdAt": "2023-05-25T14:00:12.000Z",
    "updatedAt": "2023-05-25T14:00:12.000Z"
  },
  {
    "id": 38,
    "emoji": "c10",
    "value": "<:c10:1103893306125070347>",
    "createdAt": "2023-05-25T14:00:12.000Z",
    "updatedAt": "2023-05-25T14:00:12.000Z"
  },
  {
    "id": 39,
    "emoji": "h10",
    "value": "<:h10:1103893366665662464>",
    "createdAt": "2023-05-25T14:00:12.000Z",
    "updatedAt": "2023-05-25T14:00:12.000Z"
  },
  {
    "id": 40,
    "emoji": "d10",
    "value": "<:d10:1103893419924918344>",
    "createdAt": "2023-05-25T14:00:12.000Z",
    "updatedAt": "2023-05-25T14:00:12.000Z"
  },
  {
    "id": 41,
    "emoji": "js10",
    "value": "<:js10:1103893714700607588>",
    "createdAt": "2023-05-25T14:00:12.000Z",
    "updatedAt": "2023-05-25T14:00:12.000Z"
  },
  {
    "id": 42,
    "emoji": "jc10",
    "value": "<:jc10:1103893764692529232>",
    "createdAt": "2023-05-25T14:00:12.000Z",
    "updatedAt": "2023-05-25T14:00:12.000Z"
  },
  {
    "id": 43,
    "emoji": "jh10",
    "value": "<:jh10:1103893830647943179>",
    "createdAt": "2023-05-25T14:00:12.000Z",
    "updatedAt": "2023-05-25T14:00:12.000Z"
  },
  {
    "id": 44,
    "emoji": "jd10",
    "value": "<:jd10:1103893965872304128>",
    "createdAt": "2023-05-25T14:00:12.000Z",
    "updatedAt": "2023-05-25T14:00:12.000Z"
  },
  {
    "id": 45,
    "emoji": "ks10",
    "value": "<:ks10:1103894040426053783>",
    "createdAt": "2023-05-25T14:00:12.000Z",
    "updatedAt": "2023-05-25T14:00:12.000Z"
  },
  {
    "id": 46,
    "emoji": "kc10",
    "value": "<:kc10:1103894098701725696>",
    "createdAt": "2023-05-25T14:00:12.000Z",
    "updatedAt": "2023-05-25T14:00:12.000Z"
  },
  {
    "id": 47,
    "emoji": "kh10",
    "value": "<:kh10:1103894159284240505>",
    "createdAt": "2023-05-25T14:00:12.000Z",
    "updatedAt": "2023-05-25T14:00:12.000Z"
  },
  {
    "id": 48,
    "emoji": "kd10",
    "value": "<:kd10:1103894205132177440>",
    "createdAt": "2023-05-25T14:00:12.000Z",
    "updatedAt": "2023-05-25T14:00:12.000Z"
  },
  {
    "id": 49,
    "emoji": "qc10",
    "value": "<:qc10:1103894317963149342>",
    "createdAt": "2023-05-25T14:00:12.000Z",
    "updatedAt": "2023-05-25T14:00:12.000Z"
  },
  {
    "id": 50,
    "emoji": "qh10",
    "value": "<:qh10:1103894367120412825>",
    "createdAt": "2023-05-25T14:00:12.000Z",
    "updatedAt": "2023-05-25T14:00:12.000Z"
  }
]